ryupassgen.py
ryupassgen-1.0.0.dist-info/licenses/LICENSE
ryupassgen-1.0.0.dist-info/METADATA
ryupassgen-1.0.0.dist-info/WHEEL
ryupassgen-1.0.0.dist-info/top_level.txt
ryupassgen-1.0.0.dist-info/RECORD
