Metadata-Version: 2.4
Name: ryupassgen
Version: 1.0.0
Summary: A simple random character generator that could use as passwords
Author-email: ryuzen06 <ziel26314@gmail.com>
License-Expression: MIT
Classifier: Programming Language :: Python :: 3
Classifier: Operating System :: OS Independent
Requires-Python: >=3.9
License-File: LICENSE
Dynamic: license-file
